setup.py
tlapy/__init__.py
tlapy/_version.py
tlapy.egg-info/PKG-INFO
tlapy.egg-info/SOURCES.txt
tlapy.egg-info/dependency_links.txt
tlapy.egg-info/requires.txt
tlapy.egg-info/top_level.txt